simphony/__init__.py
simphony/classical.py
simphony/exceptions.py
simphony/quantum.py
simphony/simulation.py
simphony/utils.py
simphony/libraries/__init__.py
simphony/libraries/ideal.py
simphony/libraries/sipann.py
simphony/libraries/siepic/__init__.py
simphony/libraries/siepic/models.py
simphony/libraries/siepic/source_data/PCell_parameters.xml
simphony/libraries/siepic/source_data/ebeam_y_1550.gds
"simphony/libraries/siepic/source_data/CDC/w1=440,w2=560,dW1=24,dW2=48,gap=100,p=318,N=1000,s=0,a=2.70,l1=1500,l2=1600,ln=601.dat"
"simphony/libraries/siepic/source_data/CDC/w1=440,w2=560,dW1=24,dW2=48,gap=100,p=318,N=1000,s=0,a=2.80,l1=1500,l2=1600,ln=601.dat"
"simphony/libraries/siepic/source_data/CDC/w1=440,w2=560,dW1=48,dW2=96,gap=200,p=318,N=1000,s=0,a=0.00,l1=1500,l2=1600,ln=601.dat"
"simphony/libraries/siepic/source_data/CDC/w1=450,w2=550,dW1=30,dW2=40,gap=100,p=312,N=1000,s=0,a=2.80,l1=1500,l2=1600,ln=501.dat"
"simphony/libraries/siepic/source_data/CDC/w1=450,w2=550,dW1=30,dW2=40,gap=100,p=316,N=1000,s=0,a=2.80,l1=1500,l2=1600,ln=501.dat"
"simphony/libraries/siepic/source_data/CDC/w1=450,w2=550,dW1=30,dW2=40,gap=100,p=316,N=1000,s=0,a=2.80,l1=1500,l2=1600,ln=51.dat"
"simphony/libraries/siepic/source_data/CDC/w1=450,w2=550,dW1=30,dW2=40,gap=100,p=320,N=1000,s=0,a=2.80,l1=1500,l2=1600,ln=501.dat"
"simphony/libraries/siepic/source_data/CDC/w1=450,w2=550,dW1=30,dW2=40,gap=150,p=316,N=1000,s=0,a=2.80,l1=1500,l2=1600,ln=501.dat"
"simphony/libraries/siepic/source_data/CDC/w1=450,w2=550,dW1=30,dW2=40,gap=150,p=316,N=2,s=0,a=2.80,l1=1500,l2=1600,ln=501.dat"
"simphony/libraries/siepic/source_data/CDC/w1=450,w2=550,dW1=30,dW2=40,gap=150,p=317,N=300,s=0,a=2.80,l1=1500,l2=1600,ln=51.dat"
"simphony/libraries/siepic/source_data/CDC/w1=450,w2=550,dW1=30,dW2=40,gap=150,p=320,N=1000,s=0,a=2.80,l1=1500,l2=1600,ln=501.dat"
"simphony/libraries/siepic/source_data/CDC/w1=550,w2=450,dW1=60,dW2=60,gap=220,p=320,N=1200,s=0,a=0.00,l1=1500,l2=1600,ln=501.dat"
simphony-0.7.2.dist-info/LICENSE
simphony-0.7.2.dist-info/METADATA
simphony-0.7.2.dist-info/WHEEL
simphony-0.7.2.dist-info/top_level.txt
simphony-0.7.2.dist-info/RECORD
