Metadata-Version: 2.1
Name: simphony
Version: 0.7.2
Summary: Simphony: A simulator for photonic circuits
Author: Hyrum Gunther
Author-email: Sequoia Ploeg <sequoiap4@gmail.com>, BYU CamachoLab <camacho@byu.edu>
Maintainer-email: Sequoia Ploeg <sequoiap4@gmail.com>, Christian Carver <cjcarv3r@byu.edu>, BYU CamachoLab <camacho@byu.edu>
License: MIT
Project-URL: Homepage, https://simphonyphotonics.readthedocs.io/en/stable/
Project-URL: Documentation, https://simphonyphotonics.readthedocs.io/en/stable/
Project-URL: Source, https://github.com/BYUCamachoLab/simphony
Project-URL: Bug Reports, https://github.com/BYUCamachoLab/simphony/issues
Project-URL: Research Group, https://camacholab.byu.edu/
Keywords: photonics,simulation,circuits,science,engineering,physics,interconnect
Classifier: Development Status :: 4 - Beta
Classifier: Intended Audience :: Education
Classifier: Intended Audience :: Science/Research
Classifier: Intended Audience :: Developers
Classifier: Topic :: Scientific/Engineering
Classifier: License :: OSI Approved :: MIT License
Classifier: Programming Language :: Python :: 3
Classifier: Programming Language :: Python :: 3.9
Classifier: Programming Language :: Python :: 3.10
Classifier: Programming Language :: Python :: 3.11
Classifier: Programming Language :: Python :: 3.12
Classifier: Programming Language :: Python :: 3 :: Only
Classifier: Operating System :: MacOS
Classifier: Operating System :: Microsoft :: Windows
Classifier: Operating System :: POSIX :: Linux
Classifier: Operating System :: OS Independent
Requires-Python: >=3.9
License-File: LICENSE
Requires-Dist: scipy>=1.5.4
Requires-Dist: numpy>=1.19.5
Requires-Dist: sax>=0.10.3
Requires-Dist: jax>=0.4.18
Requires-Dist: pandas>=2.0.0
Requires-Dist: lark~=1.1.5
Requires-Dist: tabulate~=0.9.0
Requires-Dist: deprecation~=2.1.0
Provides-Extra: cpu
Requires-Dist: jax[cpu]; extra == "cpu"
Provides-Extra: dev
Requires-Dist: pre-commit; extra == "dev"
Requires-Dist: matplotlib; extra == "dev"
Requires-Dist: bump2version~=1.0.0; extra == "dev"
Requires-Dist: flake8; extra == "dev"
Requires-Dist: pytest; extra == "dev"
Requires-Dist: coverage; extra == "dev"
Requires-Dist: build; extra == "dev"
Requires-Dist: tox; extra == "dev"
Provides-Extra: doc
Requires-Dist: jupyter-book~=0.13.2; extra == "doc"
Requires-Dist: matplotlib>=3.7.1; extra == "doc"
Requires-Dist: jsonschema<=4.17.3; extra == "doc"
Requires-Dist: referencing<=0.8.11; extra == "doc"
Provides-Extra: gdsfactory
Requires-Dist: gdsfactory; extra == "gdsfactory"
Provides-Extra: sipann
Requires-Dist: SiPANN; extra == "sipann"
Provides-Extra: test
Requires-Dist: pytest; extra == "test"
Requires-Dist: coverage; extra == "test"
